boris.py
client.py
setup.py
Boris.egg-info/PKG-INFO
Boris.egg-info/SOURCES.txt
Boris.egg-info/dependency_links.txt
Boris.egg-info/not-zip-safe
Boris.egg-info/requires.txt
Boris.egg-info/top_level.txt