Metadata-Version: 1.1
Name: Boris
Version: 0.1
Summary: Easily access and search Barclays bike availability in London, UK.
Home-page: http://github.com/e-dard/boris
Author: Edward Robinson
Author-email: me@eddrobinson.net
License: WTFPL
Platform: any
Classifier: Environment :: Web Environment
Classifier: Intended Audience :: Developers
Classifier: License :: Other/Proprietary License
Classifier: Operating System :: OS Independent
Classifier: Programming Language :: Python
Classifier: Topic :: Internet :: WWW/HTTP :: Dynamic Content
Classifier: Topic :: Software Development :: Libraries :: Python Modules
